ntc_ansible_plugin/__init__.py
ntc_ansible_plugin/filter_plugins/__init__.py
ntc_ansible_plugin/filter_plugins/ntc_parse.py
ntc_ansible_plugin/filter_plugins/split.py
ntc_ansible_plugin/library/__init__.py
ntc_ansible_plugin/library/get_test_info.py
ntc_ansible_plugin/library/ntc_config_command.py
ntc_ansible_plugin/library/ntc_file_copy.py
ntc_ansible_plugin/library/ntc_get_facts.py
ntc_ansible_plugin/library/ntc_install_os.py
ntc_ansible_plugin/library/ntc_reboot.py
ntc_ansible_plugin/library/ntc_rollback.py
ntc_ansible_plugin/library/ntc_save_config.py
ntc_ansible_plugin/library/ntc_show_command.py
ntc_ansible_plugin/library/ntc_validate_schema.py
ntc_ansible_plugin-0.9.4.dist-info/LICENSE
ntc_ansible_plugin-0.9.4.dist-info/METADATA
ntc_ansible_plugin-0.9.4.dist-info/WHEEL
ntc_ansible_plugin-0.9.4.dist-info/top_level.txt
ntc_ansible_plugin-0.9.4.dist-info/RECORD
