Metadata-Version: 2.1
Name: ntc-ansible-plugin
Version: 0.9.4
Summary: Dependencies for NTC Ansible modules
Home-page: https://github.com/datle1/ntc-ansible
Author: Dat Le
Author-email: datle.it@gmail.com
License: UNKNOWN
Platform: UNKNOWN
License-File: LICENSE
Requires-Dist: pynxos
Requires-Dist: pyntc
Requires-Dist: netmiko
Requires-Dist: packaging
